{
  "Id": 1,
  "Title": "Fashion Industry",
  "Content": "Lorem Ipsum is simply dummy text of the printing and typesetting industry.",
  "ImageUrl": "/images/Nike_logo_emblem_logotype 1.png"
}
{
  "Id": 2,
  "Title": "Best Design Tools",
  "Content": "Lorem Ipsum is simply dummy text of the printing and typesetting industry.",
  "ImageUrl": "/images/figma-1-logo 1.png"
}
{
  "Id": 3,
  "Title": "HR Community",
  "Content": "Lorem Ipsum is simply dummy text of the printing and typesetting industry.",
  "ImageUrl": "/images/kronos-logo-1-1 1.png"
}
